Metadata-Version: 1.0
Name: bad-functions
Version: 0.1.2
Summary: Set of bad functions in C that cause bad behavior
Home-page: UNKNOWN
Author: UNKNOWN
Author-email: UNKNOWN
License: UNKNOWN
Platform: UNKNOWN
